dictQ/__init__.py
dictQ-1.0.0.dist-info/LICENSE
dictQ-1.0.0.dist-info/METADATA
dictQ-1.0.0.dist-info/WHEEL
dictQ-1.0.0.dist-info/top_level.txt
dictQ-1.0.0.dist-info/RECORD
