Metadata-Version: 2.1
Name: dictQ
Version: 1.0.0
Summary: Sophisticate Searching Algorithms
Home-page: https://pypi.org/project/dictQ/
Author: khiat Mohammed Abderrezzak
Author-email: khiat.dev@gmail.com
License: MIT
Keywords: sorting algorithms
Classifier: Programming Language :: Python :: 3
Classifier: Operating System :: OS Independent
Classifier: License :: OSI Approved :: MIT License
Requires-Python: >=3.6
License-File: LICENSE
Requires-Dist: hashtbl (>=1.0.5)
Requires-Dist: pyfiglet (>=1.0.2)
Requires-Dist: pynput (>=1.7.7)
